kyle_portal_gun/__init__.py
kyle_portal_gun/main.py
kyle_portal_gun-0.1.0.dist-info/entry_points.txt
kyle_portal_gun-0.1.0.dist-info/METADATA
kyle_portal_gun-0.1.0.dist-info/WHEEL
kyle_portal_gun-0.1.0.dist-info/RECORD
