Metadata-Version: 2.1
Name: kyle-portal-gun
Version: 0.1.0
Summary: 
Author: Kyle Bates
Author-email: jkbates10@outlook.com
Requires-Python: >=3.12,<4.0
Classifier: Programming Language :: Python :: 3
Requires-Dist: typer[all] (>=0.9.0,<0.10.0)
